smms/__init__.py
smms/base.py
smms/user.py
smms-0.2.2.dist-info/METADATA
smms-0.2.2.dist-info/WHEEL
smms-0.2.2.dist-info/license
smms-0.2.2.dist-info/top_level.txt
smms-0.2.2.dist-info/RECORD
