Metadata-Version: 2.1
Name: smms
Version: 0.2.2
Summary: unofficial python SDK for SM.MS
Home-page: https://github.com/CNSeniorious000/SMMS4py
Author: Muspi Merol
Author-email: wjj123345567@iCloud.com
License: MIT License
License-File: license
Requires-Dist: httpx[http2]
Requires-Dist: orjson
Requires-Dist: pydantic
